Workbook

Sheet RawData
A1: Visa Revenue 2025 | B1: Visa Net Income 2025 | C1: Visa Total Debt 2025 | D1: Visa Assets 2024 | E1: Visa Assets 2025 | F1: Visa Current Assets 2025 | G1: Visa Current Liabilities 2025 | H1: Visa Equity 2024 | I1: Visa Equity 2025 | J1: Visa AR 2024 | K1: Visa AR 2025 | L1: Visa Dividends 2025 | M1: Visa EPS 2025 | N1: Visa Market Price (2026-04-24) | O1: Visa Shares Outstanding 2025 | P1: Visa LT Debt 2025 | Q1: Visa Cash 2025 | R1: Visa Operating Income 2025 | S1: Visa Interest Expense 2025 | T1: Visa PPE 2024 | U1: Visa PPE 2025 | V1: Visa Goodwill 2025 | W1: Visa Intangibles 2025 | X1: Mastercard Revenue 2025 | Y1: Mastercard Net Income 2025 | Z1: Mastercard Total Debt 2025 | AA1: Mastercard Assets 2024 | AB1: Mastercard Assets 2025 | AC1: Mastercard Current Assets 2025 | AD1: Mastercard Current Liabilities 2025 | AE1: Mastercard Equity 2024 | AF1: Mastercard Equity 2025 | AG1: Mastercard AR 2024 | AH1: Mastercard AR 2025 | AI1: Mastercard Dividends 2025 | AJ1: Mastercard EPS 2025 | AK1: Mastercard Market Price (2026-04-24) | AL1: Mastercard Shares Outstanding 2025 | AM1: Mastercard LT Debt 2025 | AN1: Mastercard Cash 2025 | AO1: Mastercard Operating Income 2025 | AP1: Mastercard Interest Expense 2025 | AQ1: Mastercard PPE 2024 | AR1: Mastercard PPE 2025 | AS1: Mastercard Goodwill 2025 | AT1: Mastercard Intangibles 2025
A2: 40000000000 | B2: 20058000000 | C2: 25171000000 | D2: 94511000000 | E2: 99627000000 | F2: 37766000000 | G2: 35048000000 | H2: 39137000000 | I2: 37909000000 | J2: 2561000000 | K2: 3126000000 | L2: 4634000000 | M2: 10.2 | N2: 308.88 | O2: 1687629770 | P2: 19602000000 | Q2: 17164000000 | R2: 23994000000 | S2: 589000000 | T2: 3824000000 | U2: 4236000000 | V2: 19879000000 | W2: 27646000000 | X2: 32791000000 | Y2: 14968000000 | Z2: 19000000000 | AA2: 48081000000 | AB2: 54157000000 | AC2: 23558000000 | AD2: 22762000000 | AE2: 6485000000 | AF2: 7737000000 | AG2: 3773000000 | AH2: 4609000000 | AI2: 2756000000 | AJ2: 16.52 | AK2: 502.38 | AL2: 885216386 | AM2: 18251000000 | AN2: 10566000000 | AO2: 18897000000 | AP2: 722000000 | AQ2: 2138000000 | AR2: 2303000000 | AS2: 9560000000 | AT2: 5382000000

Sheet Ratios
A1: Ratio | B1: Visa | C1: Mastercard | D1: Comment
A2: Net PP&E | B2: =RawData!U2 | C2: =RawData!AR2 | D2: Mastercard runs with a smaller fixed-asset base than Visa, consistent with a lighter operating footprint.
A3: Goodwill and Intangibles | B3: =RawData!V2+RawData!W2 | C3: =RawData!AS2+RawData!AT2 | D3: Visa carries a much larger intangible base, which matters when interpreting asset structure and turnover.
A4: Total Long-term Debt | B4: =RawData!P2 | C4: =RawData!AM2 | D4: Visa has a higher absolute amount of long-term debt, but Mastercard is more leveraged relative to equity.
A5: Total Debt / Total Assets | B5: =RawData!C2/RawData!E2 | C5: =RawData!Z2/RawData!AB2 | D5: Lower is less risky. Mastercard carries more debt relative to assets.
A6: Long-term Debt / Equity | B6: =RawData!P2/RawData!I2 | C6: =RawData!AM2/RawData!AF2 | D6: Mastercard looks far more leveraged because its equity base is small after buybacks.
A7: Current Ratio | B7: =RawData!F2/RawData!G2 | C7: =RawData!AC2/RawData!AD2 | D7: Both are just above 1.0, with Visa slightly safer on this measure.
A8: Quick Ratio | B8: =(RawData!Q2+RawData!K2)/RawData!G2 | C8: =(RawData!AN2+RawData!AH2)/RawData!AD2 | D8: Both are below 1.0; Mastercard is stronger on immediate liquidity.
A9: Interest Coverage | B9: =RawData!R2/RawData!S2 | C9: =RawData!AO2/RawData!AP2 | D9: Both firms comfortably cover interest expense, but Visa has the stronger safety margin.
A10: Net Profit Margin | B10: =RawData!B2/RawData!A2 | C10: =RawData!Y2/RawData!X2 | D10: Visa converts a larger share of revenue into profit.
A11: ROE | B11: =RawData!B2/AVERAGE(RawData!H2,RawData!I2) | C11: =RawData!Y2/AVERAGE(RawData!AE2,RawData!AF2) | D11: Mastercard's ROE is boosted by a very small equity base, so read with caution.
A12: ROA | B12: =RawData!B2/AVERAGE(RawData!D2,RawData!E2) | C12: =RawData!Y2/AVERAGE(RawData!AA2,RawData!AB2) | D12: Mastercard generates more profit per dollar of assets.
A13: Asset Turnover | B13: =RawData!A2/AVERAGE(RawData!D2,RawData!E2) | C13: =RawData!X2/AVERAGE(RawData!AA2,RawData!AB2) | D13: Mastercard uses its asset base more efficiently to produce revenue.
A14: Receivables Turnover | B14: =RawData!A2/AVERAGE(RawData!J2,RawData!K2) | C14: =RawData!X2/AVERAGE(RawData!AG2,RawData!AH2) | D14: Visa collects or turns receivables faster.
A15: Inventory Turnover | B15: n/a | C15: n/a | D15: n/a for both: payment networks are service businesses with no meaningful inventory.
A16: Fixed Assets Turnover | B16: =RawData!A2/AVERAGE(RawData!T2,RawData!U2) | C16: =RawData!X2/AVERAGE(RawData!AQ2,RawData!AR2) | D16: Mastercard generates more revenue per dollar of fixed assets.
A17: P/E | B17: =RawData!N2/RawData!M2 | C17: =RawData!AK2/RawData!AJ2 | D17: Very similar valuation multiples based on current market prices and FY2025 EPS.
A18: Price to Book | B18: =RawData!N2/(RawData!I2/RawData!O2) | C18: =RawData!AK2/(RawData!AF2/RawData!AL2) | D18: Mastercard's price-to-book is inflated by its low accounting equity after repurchases.
A19: Dividend Payout | B19: =RawData!L2/RawData!B2 | C19: =RawData!AI2/RawData!Y2 | D19: Visa returns a higher share of profits as dividends.

Sheet Analysis
A1: Topic | B1: Takeaway
A2: Main conclusion | B2: Visa looks stronger on financial quality; Mastercard looks stronger on efficiency.
A3: Why Visa stands out | B3: Higher net margin, stronger interest coverage, and much lower leverage relative to equity.
A4: Why Mastercard stands out | B4: Higher ROA, higher asset turnover, and higher fixed-asset turnover.
A5: Critical caution | B5: Mastercard's ROE and price-to-book are heavily distorted by low accounting equity after large buybacks.
A6: Asset structure | B6: Visa has a much larger goodwill and intangibles base, which affects asset composition and turnover interpretation.
A7: Inventory ratio | B7: Inventory turnover is not meaningful here because both firms are service-based payment networks and do not report a meaningful inventory base.
A8: Market data note | B8: Market prices used for P/E and Price-to-Book were checked on official investor quote pages on 2026-04-24.

Sheet Sources
A1: Type | B1: Source
A2: Visa 10-K 2025 | B2: https://www.sec.gov/Archives/edgar/data/1403161/000140316125000089/v-20250930.htm
A3: Mastercard 10-K 2025 | B3: https://www.sec.gov/Archives/edgar/data/1141391/000114139126000013/ma-20251231.htm
A4: Visa IR annual report | B4: https://annualreport.visa.com/annual-meeting/default.aspx
A5: Mastercard IR SEC filings | B5: https://investor.mastercard.com/financials-and-sec-filings/sec-filings/sec-filings-details/default.aspx?FilingId=19135441
A6: Visa market quote reference page | B6: https://investor.visa.com/stock-information/quote-chart/
A7: Mastercard market quote reference page | B7: https://investor.mastercard.com/stock-information/stock-data-and-chart/default.aspx
A8: Market quote note | B8: P/E and Price to Book use market prices checked on 2026-04-24 against official investor quote pages.
